obelisk/__init__.py
obelisk/app.py
py_obelisk-0.0.0.dist-info/METADATA
py_obelisk-0.0.0.dist-info/WHEEL
py_obelisk-0.0.0.dist-info/top_level.txt
py_obelisk-0.0.0.dist-info/RECORD
