Metadata-Version: 2.1
Name: py-obelisk
Version: 0.0.0
Summary: Solid Python Web Framework
Author: Mateusz Meksuła
Maintainer: Mateusz Meksuła
Classifier: Intended Audience :: Developers
Classifier: Operating System :: OS Independent
Classifier: Programming Language :: Python :: 3
Classifier: Programming Language :: Python
Classifier: Topic :: Internet
Classifier: Topic :: Software Development :: Libraries :: Application Frameworks
Classifier: Topic :: Software Development :: Libraries :: Python Modules
Classifier: Topic :: Software Development :: Libraries
Classifier: Topic :: Software Development
Classifier: Typing :: Typed
Classifier: Development Status :: 1 - Planning
Classifier: Environment :: Web Environment
Classifier: Topic :: Internet :: WWW/HTTP :: HTTP Servers
Classifier: Topic :: Internet :: WWW/HTTP
Requires-Python: >=3.9
